{
  "target_count": 20,
  "updated": "2026-06-14T08:04:43.846757+00:00",
  "candidates": [],
  "claims": [
    {
      "text": "研究表明，污水管网同时承担碳污染物输送和生物转化的双重功能，一个复杂的生物化学反应器，管道内的微生物活动可导致碳污染物在固、液、气三相之间发生显著的相间迁移（Guisasola et al",
      "section": "",
      "claim_type": "causal_claim",
      "needs": "机制文献"
    },
    {
      "text": "然而，现有研究多关注城市级污水管网系统，针对校园这一特殊功能区域的污水管网碳污染特征研究相对不足",
      "section": "",
      "claim_type": "gap_claim",
      "needs": "综述文献"
    },
    {
      "text": "早期研究主要关注管道中有机碳的生物转化过程，Guisasola等（2008）通过实验和模型模拟证实，污水在管道输送过程中，厌氧条件下的产甲烷活动可降解50%以上的有机碳，使管道成为一个重要的碳转化器",
      "section": "",
      "claim_type": "data_claim",
      "needs": "数据来源文献"
    },
    {
      "text": "然而，多数研究仅关注单一相态，缺乏对固-液-气三相碳污染物的系统性联合分析",
      "section": "",
      "claim_type": "gap_claim",
      "needs": "综述文献"
    },
    {
      "text": "现有少量研究主要集中在水质指标的基础监测层面，对碳污染物在管网中的相态分布、空间分异及其影响因素缺乏分析",
      "section": "",
      "claim_type": "gap_claim",
      "needs": "综述文献"
    },
    {
      "text": "3 现有研究不足\n\n，现有研究存在以下不足：\n\n（1）多相态联合分析不足",
      "section": "",
      "claim_type": "gap_claim",
      "needs": "综述文献"
    },
    {
      "text": "已有研究多关注单一相态的碳污染物，缺乏固-液-气三相碳污染物的系统性联合分析，难以全面揭示碳在管网中的分布特征和相间迁移规律",
      "section": "",
      "claim_type": "gap_claim",
      "needs": "综述文献"
    },
    {
      "text": "现有研究以城市级管网为主，针对校园这一特殊功能区域的碳污染特征研究较少，对不同功能区（教学区、生活区、餐饮区）碳排放差异的认识不足",
      "section": "",
      "claim_type": "gap_claim",
      "needs": "综述文献"
    },
    {
      "text": "溶解氧、温度、有机负荷等因素对碳污染物相间迁移的影响因素缺乏研究",
      "section": "",
      "claim_type": "gap_claim",
      "needs": "综述文献"
    },
    {
      "text": "4 研究内容与目标\n\n针对上述研究不足，本研究以某校园污水管网为研究对象，开展以下研究工作：\n\n（1）系统采集管道内固相、液相、气相样品，测定碳污染物各指标浓度，揭示固-液-气三相碳污染物的分布特征",
      "section": "",
      "claim_type": "gap_claim",
      "needs": "综述文献"
    },
    {
      "text": "9%，属于高变异，表明CH₄在管网空间中的分布极不均匀，存在明显的局部高浓度热点区域",
      "section": "",
      "claim_type": "data_claim",
      "needs": "数据来源文献"
    },
    {
      "text": "3%，为三种气相温室气体中空间变异最小者",
      "section": "",
      "claim_type": "data_claim",
      "needs": "数据来源文献"
    },
    {
      "text": "93%vol（n=40），变异系数仅为4",
      "section": "",
      "claim_type": "data_claim",
      "needs": "数据来源文献"
    },
    {
      "text": "18 mg/L，均值为1130",
      "section": "",
      "claim_type": "data_claim",
      "needs": "数据来源文献"
    },
    {
      "text": "51 mg/L（n=18），变异系数达247",
      "section": "",
      "claim_type": "data_claim",
      "needs": "数据来源文献"
    },
    {
      "text": "9%，为所有液相指标之最，反映了管网不同管段有机物负荷的巨大差异",
      "section": "",
      "claim_type": "data_claim",
      "needs": "数据来源文献"
    },
    {
      "text": "95 mg/L，总碳（TC）均值为114",
      "section": "",
      "claim_type": "data_claim",
      "needs": "数据来源文献"
    },
    {
      "text": "58 mg/L，其中无机碳（IC）均值为70",
      "section": "",
      "claim_type": "data_claim",
      "needs": "数据来源文献"
    },
    {
      "text": "69 mg/L，IC占TC的61",
      "section": "",
      "claim_type": "data_claim",
      "needs": "数据来源文献"
    },
    {
      "text": "2%，表明液相碳以无机碳为主要存在形态",
      "section": "",
      "claim_type": "data_claim",
      "needs": "数据来源文献"
    },
    {
      "text": "39 mg/L，铵态氮（NH₄⁺）均值为36",
      "section": "",
      "claim_type": "data_claim",
      "needs": "数据来源文献"
    },
    {
      "text": "84 mg/L，NH₄⁺占TN的78",
      "section": "",
      "claim_type": "data_claim",
      "needs": "数据来源文献"
    },
    {
      "text": "5%，说明污水中氮素以还原态氨氮为主，指示管网内部以还原性环境为主导",
      "section": "",
      "claim_type": "data_claim",
      "needs": "数据来源文献"
    },
    {
      "text": "26 mg/L（n=18），处于中低水平，进一步印证了管网水体的弱氧化至厌氧状态",
      "section": "",
      "claim_type": "data_claim",
      "needs": "数据来源文献"
    },
    {
      "text": "2%，与液相中无机碳占TC的61",
      "section": "",
      "claim_type": "data_claim",
      "needs": "数据来源文献"
    },
    {
      "text": "2%形成鲜明对比，反映了碳在不同相态中赋存形式的本质差异：固相以有机碎屑和生物膜等有机碳沉积为主，液相则以碳酸盐体系的无机碳为优势组分",
      "section": "",
      "claim_type": "data_claim",
      "needs": "数据来源文献"
    },
    {
      "text": "33 ppm）显著高于冬季（2",
      "section": "",
      "claim_type": "comparison_claim",
      "needs": "比较文献"
    },
    {
      "text": "43 ppm），增幅约74倍（Mann-Whitney U检验，p=0",
      "section": "",
      "claim_type": "data_claim",
      "needs": "数据来源文献"
    },
    {
      "text": "71 ppm）显著高于春季（550",
      "section": "",
      "claim_type": "comparison_claim",
      "needs": "比较文献"
    },
    {
      "text": "50 ppb）亦显著高于春季（426",
      "section": "",
      "claim_type": "comparison_claim",
      "needs": "比较文献"
    },
    {
      "text": "51 mg/L，相差约26倍（p<0",
      "section": "",
      "claim_type": "data_claim",
      "needs": "数据来源文献"
    },
    {
      "text": "36 mg/L）显著高于春季（0",
      "section": "",
      "claim_type": "data_claim",
      "needs": "数据来源文献"
    },
    {
      "text": "36 mg/L）显著高于春季（0",
      "section": "",
      "claim_type": "comparison_claim",
      "needs": "比较文献"
    },
    {
      "text": "气相指标中，CO₂与NO₂呈极显著正相关（r=0",
      "section": "",
      "claim_type": "data_claim",
      "needs": "数据来源文献"
    },
    {
      "text": "05）均呈显著正相关，暗示反硝化过程与水体盐度、磷营养盐之间存在耦联关系，高盐度环境可能通过抑制反硝化酶活性而促进N₂O的积累",
      "section": "",
      "claim_type": "causal_claim",
      "needs": "机制文献"
    },
    {
      "text": "液相指标中，TN与NH₄⁺的相关性最强（r=0",
      "section": "",
      "claim_type": "data_claim",
      "needs": "数据来源文献"
    },
    {
      "text": "NaCl与电导率呈极显著正相关（r=0",
      "section": "",
      "claim_type": "data_claim",
      "needs": "数据来源文献"
    },
    {
      "text": "01），表明温度升高可能促进碳酸盐平衡向释放CO₂的方向移动，导致液相无机碳降低",
      "section": "",
      "claim_type": "causal_claim",
      "needs": "机制文献"
    },
    {
      "text": "001）均与采样时间呈显著负相关，而气温与采样时间呈显著正相关（r=0",
      "section": "",
      "claim_type": "data_claim",
      "needs": "数据来源文献"
    },
    {
      "text": "9%），但在春季部分管段的贡献不可忽视",
      "section": "",
      "claim_type": "data_claim",
      "needs": "数据来源文献"
    },
    {
      "text": "2%），固相碳以有机态为主（TOC/TC=61",
      "section": "",
      "claim_type": "data_claim",
      "needs": "数据来源文献"
    },
    {
      "text": "2%），气相碳以CO₂为主导组分",
      "section": "",
      "claim_type": "data_claim",
      "needs": "数据来源文献"
    },
    {
      "text": "9%极不均匀；液相IC占TC 61",
      "section": "",
      "claim_type": "data_claim",
      "needs": "数据来源文献"
    },
    {
      "text": "2%；固相有机碳主导 | ~380字 |\n| 3",
      "section": "",
      "claim_type": "data_claim",
      "needs": "数据来源文献"
    },
    {
      "text": "2 季节差异 | CH₄春季高74倍(p=0",
      "section": "",
      "claim_type": "data_claim",
      "needs": "数据来源文献"
    },
    {
      "text": "019)；COD冬季高26倍(p<0",
      "section": "",
      "claim_type": "data_claim",
      "needs": "数据来源文献"
    },
    {
      "text": "3 耦合关系 | CO₂-NO₂强正相关(r=0",
      "section": "",
      "claim_type": "data_claim",
      "needs": "数据来源文献"
    },
    {
      "text": "Guisasola等（2008）在污水处理系统中同样观察到温度对甲烷产生的显著驱动效应，其研究表明温度每升高10°C，产甲烷速率可提高2–3倍",
      "section": "",
      "claim_type": "data_claim",
      "needs": "数据来源文献"
    },
    {
      "text": "本研究同步监测的化学需氧量（COD）数据显示，冬季COD均值高达2426 mg/L，而春季仅为93 mg/L（p<0",
      "section": "",
      "claim_type": "data_claim",
      "needs": "数据来源文献"
    },
    {
      "text": "高COD意味着冬季水体中存在大量可降解有机碳，尽管低温抑制了微生物活性，但好氧分解过程仍在持续进行，CO₂作为好氧矿化的终产物不断释放",
      "section": "",
      "claim_type": "causal_claim",
      "needs": "机制文献"
    },
    {
      "text": "Sharma等（2021）在热带城市河流研究中发现，有机碳负荷是控制CO₂排放的核心变量，高碳输入可显著提升水-气界面CO₂通量",
      "section": "",
      "claim_type": "causal_claim",
      "needs": "机制文献"
    },
    {
      "text": "冬季河道缺乏外源稀释、水动力条件较弱，有机碳在水体中累积，从而维持了较高的CO₂排放基线",
      "section": "",
      "claim_type": "gap_claim",
      "needs": "综述文献"
    },
    {
      "text": "3 氮碳耦合关系\n本研究中总氮（TN）与铵态氮（NH₄⁺）之间呈极显著正相关（r=0",
      "section": "",
      "claim_type": "data_claim",
      "needs": "数据来源文献"
    },
    {
      "text": "4 COD差异来源\n冬季COD均值为2426 mg/L，约为春季（93 mg/L）的26倍，这一悬殊差异反映了城市河道碳排放的\"底物驱动型\"特征",
      "section": "",
      "claim_type": "data_claim",
      "needs": "数据来源文献"
    },
    {
      "text": "冬季COD异常升高的原因可从多方面分析：其一，枯水期河道流量锐减，水体对污染物的稀释能力显著下降，点源排放的有机物在河道中累积；其二，冬季温度较低，微生物降解速率减缓，有机物在水体中的滞留时间延长，导致COD持续维持高位；其三，冬季城市面源污染（如落叶腐解、地表径流携带的有机碎屑）虽总量较少，但在低流量条件下其浓度贡献显著增大",
      "section": "",
      "claim_type": "causal_claim",
      "needs": "机制文献"
    },
    {
      "text": "这一发现表明，在城市河道碳排放管理中，控制有机污染输入是减少温室气体排放的关键切入点",
      "section": "",
      "claim_type": "causal_claim",
      "needs": "机制文献"
    },
    {
      "text": "首先，受研究条件限制，采样采用点位布设方式，未能实现河道全断面的空间连续监测，采样点的代表性可能受到局部水文条件（如回流区、排污口近域）的影响，导致通量估算存在一定的空间不确定性",
      "section": "",
      "claim_type": "causal_claim",
      "needs": "机制文献"
    },
    {
      "text": "N₂O是重要的温室气体之一，其增温潜势约为CO₂的265倍，且在城市河道氮转化过程中可大量产生",
      "section": "",
      "claim_type": "data_claim",
      "needs": "数据来源文献"
    },
    {
      "text": "38 ppm）升高约74倍（p=0",
      "section": "",
      "claim_type": "data_claim",
      "needs": "数据来源文献"
    },
    {
      "text": "019），液相COD冬季（2426 mg/L）较春季（93",
      "section": "",
      "claim_type": "data_claim",
      "needs": "数据来源文献"
    },
    {
      "text": "5 mg/L）高出两个数量级（p<0",
      "section": "",
      "claim_type": "data_claim",
      "needs": "数据来源文献"
    },
    {
      "text": "001），CO₂本底浓度冬季（638 ppm）显著高于春季（550 ppm）（p<0",
      "section": "",
      "claim_type": "comparison_claim",
      "needs": "比较文献"
    },
    {
      "text": "相关分析揭示碳-氮耦合与溶解氧对碳相态转化的调控作用：TN与NH₄⁺（r=0",
      "section": "",
      "claim_type": "data_claim",
      "needs": "数据来源文献"
    },
    {
      "text": "985）、CO₂与NO₂（r=0",
      "section": "",
      "claim_type": "data_claim",
      "needs": "数据来源文献"
    },
    {
      "text": "922）呈强正相关，CH₄与pH呈负相关（r=-0",
      "section": "",
      "claim_type": "data_claim",
      "needs": "数据来源文献"
    },
    {
      "text": "机制分析表明，春季升温促进产甲烷菌活性导致CH₄激增，冬季高有机负荷伴随高CO₂释放，溶解氧和有机负荷是驱动碳污染物相态转化的关键因子",
      "section": "",
      "claim_type": "causal_claim",
      "needs": "机制文献"
    }
  ],
  "bindings": [
    {
      "claim_text": "研究表明，污水管网同时承担碳污染物输送和生物转化的双重功能，一个复杂的生物化学反应器，管道内的微生物活动可导致碳污染物在固、液、气三相之间发生显著的相间迁移（Guisasola et al",
      "claim_section": "",
      "supporting_citations": [],
      "confidence": 0.0
    },
    {
      "claim_text": "然而，现有研究多关注城市级污水管网系统，针对校园这一特殊功能区域的污水管网碳污染特征研究相对不足",
      "claim_section": "",
      "supporting_citations": [],
      "confidence": 0.0
    },
    {
      "claim_text": "早期研究主要关注管道中有机碳的生物转化过程，Guisasola等（2008）通过实验和模型模拟证实，污水在管道输送过程中，厌氧条件下的产甲烷活动可降解50%以上的有机碳，使管道成为一个重要的碳转化器",
      "claim_section": "",
      "supporting_citations": [],
      "confidence": 0.0
    },
    {
      "claim_text": "然而，多数研究仅关注单一相态，缺乏对固-液-气三相碳污染物的系统性联合分析",
      "claim_section": "",
      "supporting_citations": [],
      "confidence": 0.0
    },
    {
      "claim_text": "现有少量研究主要集中在水质指标的基础监测层面，对碳污染物在管网中的相态分布、空间分异及其影响因素缺乏分析",
      "claim_section": "",
      "supporting_citations": [],
      "confidence": 0.0
    },
    {
      "claim_text": "3 现有研究不足\n\n，现有研究存在以下不足：\n\n（1）多相态联合分析不足",
      "claim_section": "",
      "supporting_citations": [],
      "confidence": 0.0
    },
    {
      "claim_text": "已有研究多关注单一相态的碳污染物，缺乏固-液-气三相碳污染物的系统性联合分析，难以全面揭示碳在管网中的分布特征和相间迁移规律",
      "claim_section": "",
      "supporting_citations": [],
      "confidence": 0.0
    },
    {
      "claim_text": "现有研究以城市级管网为主，针对校园这一特殊功能区域的碳污染特征研究较少，对不同功能区（教学区、生活区、餐饮区）碳排放差异的认识不足",
      "claim_section": "",
      "supporting_citations": [],
      "confidence": 0.0
    },
    {
      "claim_text": "溶解氧、温度、有机负荷等因素对碳污染物相间迁移的影响因素缺乏研究",
      "claim_section": "",
      "supporting_citations": [],
      "confidence": 0.0
    },
    {
      "claim_text": "4 研究内容与目标\n\n针对上述研究不足，本研究以某校园污水管网为研究对象，开展以下研究工作：\n\n（1）系统采集管道内固相、液相、气相样品，测定碳污染物各指标浓度，揭示固-液-气三相碳污染物的分布特征",
      "claim_section": "",
      "supporting_citations": [],
      "confidence": 0.0
    },
    {
      "claim_text": "9%，属于高变异，表明CH₄在管网空间中的分布极不均匀，存在明显的局部高浓度热点区域",
      "claim_section": "",
      "supporting_citations": [],
      "confidence": 0.0
    },
    {
      "claim_text": "3%，为三种气相温室气体中空间变异最小者",
      "claim_section": "",
      "supporting_citations": [],
      "confidence": 0.0
    },
    {
      "claim_text": "93%vol（n=40），变异系数仅为4",
      "claim_section": "",
      "supporting_citations": [],
      "confidence": 0.0
    },
    {
      "claim_text": "18 mg/L，均值为1130",
      "claim_section": "",
      "supporting_citations": [],
      "confidence": 0.0
    },
    {
      "claim_text": "51 mg/L（n=18），变异系数达247",
      "claim_section": "",
      "supporting_citations": [],
      "confidence": 0.0
    },
    {
      "claim_text": "9%，为所有液相指标之最，反映了管网不同管段有机物负荷的巨大差异",
      "claim_section": "",
      "supporting_citations": [],
      "confidence": 0.0
    },
    {
      "claim_text": "95 mg/L，总碳（TC）均值为114",
      "claim_section": "",
      "supporting_citations": [],
      "confidence": 0.0
    },
    {
      "claim_text": "58 mg/L，其中无机碳（IC）均值为70",
      "claim_section": "",
      "supporting_citations": [],
      "confidence": 0.0
    },
    {
      "claim_text": "69 mg/L，IC占TC的61",
      "claim_section": "",
      "supporting_citations": [],
      "confidence": 0.0
    },
    {
      "claim_text": "2%，表明液相碳以无机碳为主要存在形态",
      "claim_section": "",
      "supporting_citations": [],
      "confidence": 0.0
    },
    {
      "claim_text": "39 mg/L，铵态氮（NH₄⁺）均值为36",
      "claim_section": "",
      "supporting_citations": [],
      "confidence": 0.0
    },
    {
      "claim_text": "84 mg/L，NH₄⁺占TN的78",
      "claim_section": "",
      "supporting_citations": [],
      "confidence": 0.0
    },
    {
      "claim_text": "5%，说明污水中氮素以还原态氨氮为主，指示管网内部以还原性环境为主导",
      "claim_section": "",
      "supporting_citations": [],
      "confidence": 0.0
    },
    {
      "claim_text": "26 mg/L（n=18），处于中低水平，进一步印证了管网水体的弱氧化至厌氧状态",
      "claim_section": "",
      "supporting_citations": [],
      "confidence": 0.0
    },
    {
      "claim_text": "2%，与液相中无机碳占TC的61",
      "claim_section": "",
      "supporting_citations": [],
      "confidence": 0.0
    },
    {
      "claim_text": "2%形成鲜明对比，反映了碳在不同相态中赋存形式的本质差异：固相以有机碎屑和生物膜等有机碳沉积为主，液相则以碳酸盐体系的无机碳为优势组分",
      "claim_section": "",
      "supporting_citations": [],
      "confidence": 0.0
    },
    {
      "claim_text": "33 ppm）显著高于冬季（2",
      "claim_section": "",
      "supporting_citations": [],
      "confidence": 0.0
    },
    {
      "claim_text": "43 ppm），增幅约74倍（Mann-Whitney U检验，p=0",
      "claim_section": "",
      "supporting_citations": [],
      "confidence": 0.0
    },
    {
      "claim_text": "71 ppm）显著高于春季（550",
      "claim_section": "",
      "supporting_citations": [],
      "confidence": 0.0
    },
    {
      "claim_text": "50 ppb）亦显著高于春季（426",
      "claim_section": "",
      "supporting_citations": [],
      "confidence": 0.0
    },
    {
      "claim_text": "51 mg/L，相差约26倍（p<0",
      "claim_section": "",
      "supporting_citations": [],
      "confidence": 0.0
    },
    {
      "claim_text": "36 mg/L）显著高于春季（0",
      "claim_section": "",
      "supporting_citations": [],
      "confidence": 0.0
    },
    {
      "claim_text": "36 mg/L）显著高于春季（0",
      "claim_section": "",
      "supporting_citations": [],
      "confidence": 0.0
    },
    {
      "claim_text": "气相指标中，CO₂与NO₂呈极显著正相关（r=0",
      "claim_section": "",
      "supporting_citations": [],
      "confidence": 0.0
    },
    {
      "claim_text": "05）均呈显著正相关，暗示反硝化过程与水体盐度、磷营养盐之间存在耦联关系，高盐度环境可能通过抑制反硝化酶活性而促进N₂O的积累",
      "claim_section": "",
      "supporting_citations": [],
      "confidence": 0.0
    },
    {
      "claim_text": "液相指标中，TN与NH₄⁺的相关性最强（r=0",
      "claim_section": "",
      "supporting_citations": [],
      "confidence": 0.0
    },
    {
      "claim_text": "NaCl与电导率呈极显著正相关（r=0",
      "claim_section": "",
      "supporting_citations": [],
      "confidence": 0.0
    },
    {
      "claim_text": "01），表明温度升高可能促进碳酸盐平衡向释放CO₂的方向移动，导致液相无机碳降低",
      "claim_section": "",
      "supporting_citations": [],
      "confidence": 0.0
    },
    {
      "claim_text": "001）均与采样时间呈显著负相关，而气温与采样时间呈显著正相关（r=0",
      "claim_section": "",
      "supporting_citations": [],
      "confidence": 0.0
    },
    {
      "claim_text": "9%），但在春季部分管段的贡献不可忽视",
      "claim_section": "",
      "supporting_citations": [],
      "confidence": 0.0
    },
    {
      "claim_text": "2%），固相碳以有机态为主（TOC/TC=61",
      "claim_section": "",
      "supporting_citations": [],
      "confidence": 0.0
    },
    {
      "claim_text": "2%），气相碳以CO₂为主导组分",
      "claim_section": "",
      "supporting_citations": [],
      "confidence": 0.0
    },
    {
      "claim_text": "9%极不均匀；液相IC占TC 61",
      "claim_section": "",
      "supporting_citations": [],
      "confidence": 0.0
    },
    {
      "claim_text": "2%；固相有机碳主导 | ~380字 |\n| 3",
      "claim_section": "",
      "supporting_citations": [],
      "confidence": 0.0
    },
    {
      "claim_text": "2 季节差异 | CH₄春季高74倍(p=0",
      "claim_section": "",
      "supporting_citations": [],
      "confidence": 0.0
    },
    {
      "claim_text": "019)；COD冬季高26倍(p<0",
      "claim_section": "",
      "supporting_citations": [],
      "confidence": 0.0
    },
    {
      "claim_text": "3 耦合关系 | CO₂-NO₂强正相关(r=0",
      "claim_section": "",
      "supporting_citations": [],
      "confidence": 0.0
    },
    {
      "claim_text": "Guisasola等（2008）在污水处理系统中同样观察到温度对甲烷产生的显著驱动效应，其研究表明温度每升高10°C，产甲烷速率可提高2–3倍",
      "claim_section": "",
      "supporting_citations": [],
      "confidence": 0.0
    },
    {
      "claim_text": "本研究同步监测的化学需氧量（COD）数据显示，冬季COD均值高达2426 mg/L，而春季仅为93 mg/L（p<0",
      "claim_section": "",
      "supporting_citations": [],
      "confidence": 0.0
    },
    {
      "claim_text": "高COD意味着冬季水体中存在大量可降解有机碳，尽管低温抑制了微生物活性，但好氧分解过程仍在持续进行，CO₂作为好氧矿化的终产物不断释放",
      "claim_section": "",
      "supporting_citations": [],
      "confidence": 0.0
    },
    {
      "claim_text": "Sharma等（2021）在热带城市河流研究中发现，有机碳负荷是控制CO₂排放的核心变量，高碳输入可显著提升水-气界面CO₂通量",
      "claim_section": "",
      "supporting_citations": [],
      "confidence": 0.0
    },
    {
      "claim_text": "冬季河道缺乏外源稀释、水动力条件较弱，有机碳在水体中累积，从而维持了较高的CO₂排放基线",
      "claim_section": "",
      "supporting_citations": [],
      "confidence": 0.0
    },
    {
      "claim_text": "3 氮碳耦合关系\n本研究中总氮（TN）与铵态氮（NH₄⁺）之间呈极显著正相关（r=0",
      "claim_section": "",
      "supporting_citations": [],
      "confidence": 0.0
    },
    {
      "claim_text": "4 COD差异来源\n冬季COD均值为2426 mg/L，约为春季（93 mg/L）的26倍，这一悬殊差异反映了城市河道碳排放的\"底物驱动型\"特征",
      "claim_section": "",
      "supporting_citations": [],
      "confidence": 0.0
    },
    {
      "claim_text": "冬季COD异常升高的原因可从多方面分析：其一，枯水期河道流量锐减，水体对污染物的稀释能力显著下降，点源排放的有机物在河道中累积；其二，冬季温度较低，微生物降解速率减缓，有机物在水体中的滞留时间延长，导致COD持续维持高位；其三，冬季城市面源污染（如落叶腐解、地表径流携带的有机碎屑）虽总量较少，但在低流量条件下其浓度贡献显著增大",
      "claim_section": "",
      "supporting_citations": [],
      "confidence": 0.0
    },
    {
      "claim_text": "这一发现表明，在城市河道碳排放管理中，控制有机污染输入是减少温室气体排放的关键切入点",
      "claim_section": "",
      "supporting_citations": [],
      "confidence": 0.0
    },
    {
      "claim_text": "首先，受研究条件限制，采样采用点位布设方式，未能实现河道全断面的空间连续监测，采样点的代表性可能受到局部水文条件（如回流区、排污口近域）的影响，导致通量估算存在一定的空间不确定性",
      "claim_section": "",
      "supporting_citations": [],
      "confidence": 0.0
    },
    {
      "claim_text": "N₂O是重要的温室气体之一，其增温潜势约为CO₂的265倍，且在城市河道氮转化过程中可大量产生",
      "claim_section": "",
      "supporting_citations": [],
      "confidence": 0.0
    },
    {
      "claim_text": "38 ppm）升高约74倍（p=0",
      "claim_section": "",
      "supporting_citations": [],
      "confidence": 0.0
    },
    {
      "claim_text": "019），液相COD冬季（2426 mg/L）较春季（93",
      "claim_section": "",
      "supporting_citations": [],
      "confidence": 0.0
    },
    {
      "claim_text": "5 mg/L）高出两个数量级（p<0",
      "claim_section": "",
      "supporting_citations": [],
      "confidence": 0.0
    },
    {
      "claim_text": "001），CO₂本底浓度冬季（638 ppm）显著高于春季（550 ppm）（p<0",
      "claim_section": "",
      "supporting_citations": [],
      "confidence": 0.0
    },
    {
      "claim_text": "相关分析揭示碳-氮耦合与溶解氧对碳相态转化的调控作用：TN与NH₄⁺（r=0",
      "claim_section": "",
      "supporting_citations": [],
      "confidence": 0.0
    },
    {
      "claim_text": "985）、CO₂与NO₂（r=0",
      "claim_section": "",
      "supporting_citations": [],
      "confidence": 0.0
    },
    {
      "claim_text": "922）呈强正相关，CH₄与pH呈负相关（r=-0",
      "claim_section": "",
      "supporting_citations": [],
      "confidence": 0.0
    },
    {
      "claim_text": "机制分析表明，春季升温促进产甲烷菌活性导致CH₄激增，冬季高有机负荷伴随高CO₂释放，溶解氧和有机负荷是驱动碳污染物相态转化的关键因子",
      "claim_section": "",
      "supporting_citations": [],
      "confidence": 0.0
    }
  ]
}